MANIFEST.in
README
setup.py
test/__init__.py
test/__init__.pyc
test/test_differ.py
test/__pycache__/test_differ.cpython-27-PYTEST.pyc
tiddlywebplugins/__init__.py
tiddlywebplugins/differ.py
tiddlywebplugins.differ.egg-info/PKG-INFO
tiddlywebplugins.differ.egg-info/SOURCES.txt
tiddlywebplugins.differ.egg-info/dependency_links.txt
tiddlywebplugins.differ.egg-info/namespace_packages.txt
tiddlywebplugins.differ.egg-info/not-zip-safe
tiddlywebplugins.differ.egg-info/requires.txt
tiddlywebplugins.differ.egg-info/top_level.txt