Metadata-Version: 1.0
Name: tiddlywebplugins.differ
Version: 0.6.4
Summary: TiddlyWeb plugin to compare tiddler revisions
Home-page: http://pypi.python.org/pypi/tiddlywebplugins.differ
Author: FND
Author-email: FNDo@gmx.net
License: UNKNOWN
Platform: Posix; MacOS X; Windows
